CHANGELOG.txt
LICENSE.txt
MANIFEST.in
README.txt
setup.py
shreycalc/__init__.py
shreycalc.egg-info/PKG-INFO
shreycalc.egg-info/SOURCES.txt
shreycalc.egg-info/dependency_links.txt
shreycalc.egg-info/top_level.txt