Metadata-Version: 2.1
Name: shreycalc
Version: 0.0.1
Summary: A very basic calculator
Home-page: UNKNOWN
Author: Shrey Khandelwal
Author-email: shreykhandelwal14@yahoo.com
License: MIT
Keywords: calculator
Platform: UNKNOWN
Classifier: Development Status :: 5 - Production/Stable
Classifier: Intended Audience :: Education
Classifier: Operating System :: MacOS :: MacOS X
Classifier: License :: OSI Approved :: MIT License
Classifier: Programming Language :: Python :: 3
License-File: LICENSE.txt
